chyslivnyk/__init__.py
chyslivnyk-0.1.0.dist-info/licenses/LICENSE
chyslivnyk-0.1.0.dist-info/METADATA
chyslivnyk-0.1.0.dist-info/WHEEL
chyslivnyk-0.1.0.dist-info/top_level.txt
chyslivnyk-0.1.0.dist-info/RECORD
