Metadata-Version: 2.4
Name: chyslivnyk
Version: 0.1.0
Summary: A Python library for handling Ukrainian numerals (chyslivnyky) designed to convert numeric values into their textual representations in Ukrainian, taking into account grammatical features such as case, gender, and number.
Author-email: Anton Sikidin <anton.sikidin@gmail.com>
Project-URL: Homepage, https://github.com/AntonSikidin/Chyslivnyk
Project-URL: Issues, https://github.com/AntonSikidin/Chyslivnyk/issues
Keywords: ukrainian,numerals,chyslivnyk
Classifier: Programming Language :: Python :: 3
Classifier: Operating System :: OS Independent
Classifier: Topic :: Software Development :: Libraries :: Python Modules
Classifier: Intended Audience :: Developers
Classifier: Natural Language :: Ukrainian
Requires-Python: >=3.7
License-File: LICENSE
Dynamic: license-file
